convertor/__init__.py
convertor/convertor.py
convertor-1.0.dist-info/METADATA
convertor-1.0.dist-info/WHEEL
convertor-1.0.dist-info/top_level.txt
convertor-1.0.dist-info/RECORD
